vsrealesrgan/__init__.py
vsrealesrgan/__main__.py
vsrealesrgan/arch_util.py
vsrealesrgan/rrdbnet_arch.py
vsrealesrgan/srvgg_arch.py
vsrealesrgan/models/Ani4Kv2_Compact_2x.pth
vsrealesrgan/models/Ani4Kv2_UltraCompact_2x.pth
vsrealesrgan/models/AniScale2_Compact_2x.pth
vsrealesrgan/models/AniScale2_Refiner_1x.pth
vsrealesrgan/models/Anime1080Fixer_SuperUltraCompact_1x.pth
vsrealesrgan/models/AnimeJaNai_HD_V3Sharp1_Compact_2x.pth
vsrealesrgan/models/AnimeJaNai_HD_V3Sharp1_SuperUltraCompact_2x.pth
vsrealesrgan/models/AnimeJaNai_HD_V3Sharp1_UltraCompact_2x.pth
vsrealesrgan/models/AnimeJaNai_HD_V3_Compact_2x.pth
vsrealesrgan/models/AnimeJaNai_HD_V3_SuperUltraCompact_2x.pth
vsrealesrgan/models/AnimeJaNai_HD_V3_UltraCompact_2x.pth
vsrealesrgan/models/AnimeJaNai_SD_V1beta34_Compact_2x.pth
vsrealesrgan/models/AnimeJaNai_V2_Compact_2x.pth
vsrealesrgan/models/AnimeJaNai_V2_SuperUltraCompact_2x.pth
vsrealesrgan/models/AnimeJaNai_V2_UltraCompact_2x.pth
vsrealesrgan/models/ESRGAN_SRx4.pth
vsrealesrgan/models/LDVDeNoise_35mm_Compact.pth
vsrealesrgan/models/OpenProteus_Compact_2x.pth
vsrealesrgan/models/RealESRGAN_x2plus.pth
vsrealesrgan/models/RealESRGAN_x4plus.pth
vsrealesrgan/models/RealESRGAN_x4plus_anime_6B.pth
vsrealesrgan/models/cHiDeNoise_Compact.pth
vsrealesrgan/models/realesr_animevideov3.pth
vsrealesrgan/models/realesr_general_wdn_x4v3.pth
vsrealesrgan/models/realesr_general_x4v3.pth
vsrealesrgan-5.2.1.dist-info/METADATA
vsrealesrgan-5.2.1.dist-info/WHEEL
vsrealesrgan-5.2.1.dist-info/licenses/LICENSE
vsrealesrgan-5.2.1.dist-info/RECORD
