Metadata-Version: 2.4
Name: vsrealesrgan
Version: 5.2.1
Summary: Real-ESRGAN function for VapourSynth
Project-URL: Homepage, https://github.com/HolyWu/vs-realesrgan
Project-URL: Issues, https://github.com/HolyWu/vs-realesrgan/issues
Author-email: HolyWu <holywu@gmail.com>
License-File: LICENSE
Keywords: PyTorch,Real-ESRGAN,TensorRT,VapourSynth
Classifier: Environment :: GPU :: NVIDIA CUDA
Classifier: License :: OSI Approved :: BSD License
Classifier: Operating System :: OS Independent
Classifier: Programming Language :: Python :: 3
Classifier: Topic :: Multimedia :: Video
Requires-Python: >=3.10
Requires-Dist: numpy
Requires-Dist: requests
Requires-Dist: torch>=2.6.0.dev
Requires-Dist: tqdm
Requires-Dist: vapoursynth>=66
